rl/__init__.py
rl/__version__.py
rl_tutorial-0.0.1.dist-info/METADATA
rl_tutorial-0.0.1.dist-info/WHEEL
rl_tutorial-0.0.1.dist-info/licenses/LICENSE
rl_tutorial-0.0.1.dist-info/RECORD
